{
  "schemaVersion": 1,
  "id": "edgejump",
  "version": "${version}",

  "name": "EdgeJump",
  "description": "Automatically jumps at the edge of a block, plain simple.",
  "authors": [
    "Yan01h (Hydra/Hydrated Dragon)"
  ],
  "contact": {
    "homepage": "https://github.com/Yan01h/EdgeJump",
    "sources": "https://github.com/Yan01h/EdgeJump"
  },

  "license": "CC0-1.0",
  "icon": "assets/edgejump/icon.png",

  "environment": "client",
  "entrypoints": {
    "client": [
      "net.yan01h.edgejump.EdgeJump"
    ]
  },
  "mixins": [
    "edgejump.mixins.json"
  ],

  "depends": {
    "fabricloader": ">=0.14.6",
    "fabric": "*",
    "minecraft": "~1.18.2",
    "java": ">=17"
  },
  "suggests": {
    "another-mod": "*"
  }
}
